llama_index/storage/index_store/postgres/__init__.py
llama_index/storage/index_store/postgres/base.py
llama_index_storage_index_store_postgres-0.5.0.dist-info/METADATA
llama_index_storage_index_store_postgres-0.5.0.dist-info/WHEEL
llama_index_storage_index_store_postgres-0.5.0.dist-info/licenses/LICENSE
llama_index_storage_index_store_postgres-0.5.0.dist-info/RECORD
